{
  "message_id": "<caa41577-d966-4f9b-b2af-6748302f425dn@googlegroups.com>",
  "thread_id": "<4FF3EE9D-C36A-4445-9093-608F1C615642@gmail.com>",
  "subject": "Re: taking a break",
  "sender": "\"thomas.la...@gmail.com\" <thomas.laughliniii@gmail.com>",
  "date": "Sat, 31 Jan 2026 16:07:59 -0800 (PST)",
  "body": "Hi Alister,\r\n\r\nThank you for all your help and encouragement over the years on this forum \r\nand the Dynamo message boards!\r\n\r\nI know many of my projects would not have been possible without your \r\ntutorials, quick replies, and python libraries.\r\n\r\nEnjoy the break!\r\n\r\nThere should be plenty of collective knowledge in the community to field \r\nquestions in your absence.\r\n \r\nCheers!\r\n-Tom\r\n\r\nOn Friday, January 30, 2026 at 10:06:13 PM UTC-8 alist...@gmail.com wrote:\r\n\r\n> Hi all,\r\n>\r\n> I’m about to take an extended break from work so won’t be responding to \r\n> any messages about warp/tomography/subtomogram averaging.\r\n>\r\n> Apologies if you’ve been left hanging recently, I know I’ve not been on \r\n> top of the mailing list/github issues.\r\n>\r\n> Tomography is still tough, please be generous with your knowledge if you \r\n> see someone asking for help.\r\n>\r\n> Take care and happy processing,\r\n>\r\n> Alister\r\n>\r\n> Sent from mobile - apologies for brevity"
}