{
  "message_id": "<7f103c63-5264-49bb-9ec3-3307a2b86ac8n@googlegroups.com>",
  "thread_id": "",
  "subject": "MTools: importing population from Windows WARP",
  "sender": "Jesse Hansen <bluufive@gmail.com>",
  "date": "Fri, 19 Jul 2024 03:35:16 -0700 (PDT)",
  "body": "hi all,\n\nI have processed my data already in windows WARP, but now I'd like to pick \nup on Linux M.  Is that possible, or do I need to start over processing \nfresh in WarpTools?\n\nI have gone through WarpTools tutorial so I know all functionality is \ngood.  \n\nFor my data, I cannot create the data source where I point to my WARP \nprevious.settings file.  When it runs I get the output below:\n\njhansen@gpu144$ ./datasource.sh \nRunning command create_source with:\npopulation = m/mydata.population\nprocessing_settings = previous.settings\nname = mydata\nnframes = \nfiles = \n\nLooking for data... Unhandled exception. System.ArgumentException: The \nvalue cannot be an empty string. (Parameter 'path')\n   at System.ArgumentException.ThrowNullOrEmptyException(String argument, \nString paramName)\n   at System.IO.Path.GetFullPath(String path)\n   at System.IO.Enumeration.FileSystemEnumerator`1..ctor(String directory, \nBoolean isNormalized, EnumerationOptions options)\n   at System.IO.Enumeration.FileSystemEnumerable`1..ctor(String directory, \nFindTransform transform, EnumerationOptions options, Boolean isNormalized)\n   at System.IO.Enumeration.FileSystemEnumerableFactory.UserFiles(String \ndirectory, String expression, EnumerationOptions options)\n   at System.IO.Directory.InternalEnumeratePaths(String path, String \nsearchPattern, SearchTarget searchTarget, EnumerationOptions options)\n   at MTools.Commands.CreateSource.Run(Object options) in \n(path)/warp/MTools/Commands/CreateSource.cs:line 108\n   at MTools.MTools.Run(Object options) in \n(path)/warp/MTools/MTools.cs:line 32\n   at CommandLine.ParserResultExtensions.WithParsed[T](ParserResult`1 \nresult, Action`1 action)\n   at MTools.MTools.Main(String[] args) in \n(path)/warp/MTools/MTools.cs:line 21\n./02.sh: line 4: 492165 Aborted                 MTools create_source --name \nmydata --population m/mydata.population --processing_settings \nprevious.settings\n\nany help is appreciated,\n\nbest,\n\nJesse"
}