{
  "message_id": "<5e4ba38e-d5f8-4e53-b663-b81507a81974n@googlegroups.com>",
  "thread_id": "<8e4f8559-d237-d1e7-1b40-1e7651ed4b64@fz-juelich.de>",
  "subject": "Re: EER files do not update with recursive search in Warp 1.1.0\r\n Beta",
  "sender": "\"teg...@gmail.com\" <tegunov@gmail.com>",
  "date": "Mon, 19 Sep 2022 08:42:37 -0700 (PDT)",
  "body": "Hi Daniel,\r\n\r\nIs this happening only if you point it to EER files in that location? \r\nGenerally, some Linux FS setups still cause the file discovery mechanism to \r\nbreak from time to time. Hard to debug without access to such a setup.\r\n\r\nCheers,\r\nDimitry\r\n\r\nOn Sunday, September 18, 2022 at 1:16:37 AM UTC+5 d.m...@fz-juelich.de \r\nwrote:\r\n\r\n> Hi all,\r\n>\r\n> love the new Ukraine themed Warp Version, but it's giving me some problems \r\n> with EER files from FalconIV/EPU.\r\n>\r\n> When I'm using recursive processing with EPUs GridSquare*/Data/*eer format \r\n> it finds initial images and processes them fine when pointed to the \r\n> Images-Disc1 folder. However, the file list is not updating although new \r\n> images keep flying in. When I stop processing and refresh the folder \r\n> manually it finds the new images. My processing folder is different from my \r\n> data folder.\r\n>\r\n> When I untick the \"Search recursively\" option and go to the \r\n> Gridsquare*/Data/ folder it keeps updating and works fine on-the-fly.\r\n>\r\n> Of course this can be fixed with some quick linux mv commands, but I still \r\n> wanted to report it.\r\n>\r\n> Cheers,\r\n>\r\n> Dan\r\n>\r\n> -- \r\n> Dr. Daniel Mann\r\n>\r\n> Forschungszentrum Jülich GmbH\r\n> Ernst-Ruska Centre for Microscopy and Spectroscopy with Electrons / ER-C-3 Structural Biology\r\n> Institute for Biological Information Processing / IBI-6 Cellular Structural Biology\r\n> Wilhem-Johnen-Straße, 52425 Jülich, Germany\r\n> Phone: +49 2461 61 9499 <+49%202461%20619499>https://go.fzj.de/erc3-ibi6\r\n> Email: d.m...@fz-juelich.de\r\n>\r\n>"
}