{
  "message_id": "<52ceb8ac-1f94-45f7-8131-c3b41e508830n@googlegroups.com>",
  "thread_id": "<f68df150-1bc7-4bb0-ba54-10439c59d2a2n@googlegroups.com>",
  "subject": "Re: CTF correction in WARP",
  "sender": "\"teg...@gmail.com\" <tegunov@gmail.com>",
  "date": "Tue, 27 Sep 2022 09:44:50 -0700 (PDT)",
  "body": "Hi Julien,\r\n\r\nThe CTF of the images in the average folder is not modified, so they're not \r\nphase-flipped and not Wiener-filtered. There is no easy way to get such \r\nimages out of Warp. A hack that might work for this is to create a fake \r\ntilt series from every individual micrograph (1 tilt per series), go \r\nthrough the tilt series pipeline, and then reconstruct very thin tomograms. \r\nYou'd still have to flatten the resulting volumes along Z manually since \r\nthe smallest Z dimension Warp will let you choose is 2. Phase flipping is \r\napplied based on local defocus values during tomogram reconstruction, and \r\nyou can get Wiener filtering by enabling deconvolution.\r\n\r\nHowever, I'm not sure this is the best way to go for the pipeline you \r\nenvision. If you want to reconstruct in IMOD, it's best to also let it \r\nhandle the CTF. If you're using IMOD for reconstruction because Warp \r\nup-weights high frequencies in a weird way in its reconstructions, you \r\nmight want to try the new 1.1.0 where this bug is fixed (not really a bug, \r\nmore of a side effect of the algorithm used).\r\n\r\nCheers,\r\nDimitry\r\n\r\nOn Tuesday, September 27, 2022 at 1:50:58 AM UTC-7 julien....@gmail.com \r\nwrote:\r\n\r\n> Sorry to ask again but does anyone know if images from *average* *folder* \r\n> are* phase flipped* ? *wiener filtered* ? or just* raw frames aligned* ?\r\n>\r\n> Thank you\r\n>\r\n> Le lundi 5 septembre 2022 à 14:56:50 UTC+2, Julien Maufront a écrit :\r\n>\r\n>> (Note : I picked/extracted the particles out of WARP with EMAN)\r\n>>\r\n>> Le lundi 5 septembre 2022 à 11:04:42 UTC+2, Julien Maufront a écrit :\r\n>>\r\n>>> Hi everyone,\r\n>>>\r\n>>> I have a naive question concerning the use of CTF fitting from WARP :\r\n>>>\r\n>>> Are the micrographs from the \"*average*\" folder CTF corrected ? Or are \r\n>>> they just raw frames alignment results ?\r\n>>>\r\n>>> Indeed, I processed a dataset made of 2D movies in WARP (frames \r\n>>> alignment/CTF fitting).\r\n>>> I then picked/extracted particles out of the micrographs contained in \r\n>>> the *average* folder to use the generated stack for 2D \r\n>>> alignment/classification.\r\n>>>\r\n>>> Do I need to had a CTF correction step of my particles ?\r\n>>>\r\n>>> Similarly, can the tomograms generated by IMOD out of tilt series \r\n>>> pre-processed in WARP be considered as CTF corrected ?\r\n>>>\r\n>>> If not, how should we use the *powerspectrum* files to do the CTF \r\n>>> correction step ?\r\n>>>\r\n>>>\r\n>>> Thanks in advance for your help,\r\n>>> Julien Maufront\r\n>>>\r\n>>"
}